simpy_helpers/Debug.py
simpy_helpers/Entity.py
simpy_helpers/Resource.py
simpy_helpers/Source.py
simpy_helpers/Stats.py
simpy_helpers/__init__.py
simpy_helpers-1.2.0.dist-info/LICENSE
simpy_helpers-1.2.0.dist-info/METADATA
simpy_helpers-1.2.0.dist-info/WHEEL
simpy_helpers-1.2.0.dist-info/top_level.txt
simpy_helpers-1.2.0.dist-info/RECORD
