Metadata-Version: 2.1
Name: simpy-helpers
Version: 1.2.0
Summary: A package to help simplify simpy simulation
Home-page: https://github.com/bambielli/simpy_helpers
Author: Brian Ambielli
Author-email: brian.ambielli@gmail.com
License: UNKNOWN
Platform: UNKNOWN
Classifier: Programming Language :: Python :: 3
Classifier: License :: OSI Approved :: MIT License
Classifier: Operating System :: OS Independent
Requires-Python: >=3.6
Requires-Dist: simpy (<=5,>=3)
Requires-Dist: numpy
